solcast/__init__.py
solcast/api.py
solcast/forecast.py
solcast/historic.py
solcast/live.py
solcast/pv_power_sites.py
solcast/tmy.py
solcast/unmetered_locations.py
solcast/urls.py
solcast-1.2.5.dist-info/METADATA
solcast-1.2.5.dist-info/WHEEL
solcast-1.2.5.dist-info/licenses/LICENSE
solcast-1.2.5.dist-info/RECORD
