Metadata-Version: 2.3
Name: solcast
Version: 1.2.5
Summary: a simple Python SDK for the Solcast API
Project-URL: Homepage, https://pypi.org/project/solcast/
Project-URL: Documentation, https://solcast.github.io/solcast-api-python-sdk
Project-URL: Repository, https://github.com/Solcast/solcast-api-python-sdk
License-Expression: Apache-2.0
License-File: LICENSE
Classifier: Development Status :: 4 - Beta
Classifier: Intended Audience :: Developers
Classifier: Intended Audience :: Information Technology
Classifier: License :: OSI Approved :: Apache Software License
Classifier: Operating System :: OS Independent
Classifier: Programming Language :: Python
Classifier: Programming Language :: Python :: 3
Classifier: Programming Language :: Python :: 3 :: Only
Classifier: Programming Language :: Python :: 3.7
Classifier: Programming Language :: Python :: 3.8
Classifier: Programming Language :: Python :: 3.9
Classifier: Programming Language :: Python :: 3.10
Classifier: Programming Language :: Python :: 3.11
Classifier: Topic :: Internet
Classifier: Topic :: Scientific/Engineering
Classifier: Topic :: Software Development
Classifier: Topic :: Software Development :: Libraries
Classifier: Topic :: Software Development :: Libraries :: Python Modules
Classifier: Typing :: Typed
Requires-Python: >=3.7
Provides-Extra: all
Requires-Dist: black; extra == 'all'
Requires-Dist: kaleido; extra == 'all'
Requires-Dist: matplotlib; extra == 'all'
Requires-Dist: mkdocs; extra == 'all'
Requires-Dist: mkdocs-jupyter; extra == 'all'
Requires-Dist: mkdocs-material; extra == 'all'
Requires-Dist: mkdocstrings[python]==0.22; extra == 'all'
Requires-Dist: notebook; extra == 'all'
Requires-Dist: pandas; extra == 'all'
Requires-Dist: pytest; extra == 'all'
Provides-Extra: docs
Requires-Dist: kaleido; extra == 'docs'
Requires-Dist: mkdocs; extra == 'docs'
Requires-Dist: mkdocs-jupyter; extra == 'docs'
Requires-Dist: mkdocs-material; extra == 'docs'
Requires-Dist: mkdocstrings[python]==0.22; extra == 'docs'
Requires-Dist: pytest; extra == 'docs'
